encryptions/__init__.py
encryptions/encryption.py
tests/__init__.py
tests/test_encryption.py
encryptions-1.0.0.dist-info/METADATA
encryptions-1.0.0.dist-info/WHEEL
encryptions-1.0.0.dist-info/top_level.txt
encryptions-1.0.0.dist-info/RECORD
