Metadata-Version: 2.2
Name: encryptions
Version: 1.0.0
Summary: A simple AES and RSA encryption package
Home-page: https://github.com/BhargavLimbad786/Encryption
Author: Bhargav Limbad
Author-email: bhargav@e6x.io
Classifier: Programming Language :: Python :: 3
Classifier: License :: OSI Approved :: Apache Software License
Classifier: Operating System :: OS Independent
Requires-Python: >=3.6
Requires-Dist: pycryptodome
Dynamic: author
Dynamic: author-email
Dynamic: classifier
Dynamic: description
Dynamic: description-content-type
Dynamic: home-page
Dynamic: requires-dist
Dynamic: requires-python
Dynamic: summary
